{
  "publishDate": "2026-07-17T23:08:00.000Z",
  "clicks": 0,
  "customJs": "",
  "searchIntent": "",
  "updatedAt": "2026-07-18T02:58:45.850Z",
  "category": "미국 증시",
  "id": "1784290871961",
  "naverIndexStatus": "requested",
  "status": "published",
  "flowType": "과거에서 찾는 답",
  "language": "ko",
  "seoDescription": "미국 CME 나스닥 선물의 제도적 투자방법을 정밀 분석합니다. 해외선물 계좌 개설 요건, NQ와 MNQ 규격 및 틱가치 비교, 개시·유지증거금 원리와 마진콜 대응 리스크 관리를 규명합니다.",
  "tags": [
    "나스닥선물투자방법",
    "해외선물계좌개설",
    "E-mini나스닥",
    "MicroE-mini",
    "계약승수원리",
    "틱가치변동",
    "개시증거금",
    "유지증거금마지노선",
    "마진콜강제청산",
    "지정가주문",
    "스탑로스손절",
    "롤오버월물교체"
  ],
  "seoTitle": "나스닥 선물 투자방법: 계좌 개설부터 증거금 관리까지 완벽 가이드",
  "categorySlug": "nasdaq-futures",
  "structuredDataJsonLd": "",
  "secondaryKeywords": [
    "ETF",
    "해외선물",
    "CFD",
    "레버리지 ETF"
  ],
  "postViews": 4,
  "createdAt": "2026-07-17T12:21:11.684Z",
  "authorId": "Jg6IvXtLOCclLRU7EzhZGTqMXb52",
  "slug": "nasdaq-futures-investing",
  "content": "<p data-ke-size=\"size8\">&nbsp;</p>\n<div style=\"font-family: 'Noto Sans KR', sans-serif; line-height: 1.75; max-width: 800px; margin: 0 auto; font-size: 16px; box-sizing: border-box; color: #2c3e50;\">\n\n    \n    <div style=\"background-color: #f8f9fa; border-left: 4px solid #1a73e8; padding: 20px; border-radius: 4px; margin-bottom: 30px; font-size: 15px; color: #4a5568; line-height: 1.6;\">\n        해외선물 시장의 중심에 있는 <strong>'나스닥 선물 투자방법'</strong>의 제도적 절차와 핵심 운용 메커니즘을 다룹니다. 계좌 개설부터 NQ와 MNQ의 규격 비교, 증거금 관리의 마지노선, 그리고 만기 포지션 이전을 위한 롤오버(Rollover)까지 금융 지식 라이브러리 포맷으로 명쾌하게 정리해 드립니다.\n    </div>\n\n    \n    <p style=\"margin-bottom: 18px;\">글로벌 빅테크 기업들의 강력한 성장세에 힘입어 미국 증시에 관심을 가지는 투자자들이 체계적으로 늘어나고 있습니다. 그중에서도 계약 명목가치 전액이 아닌 증거금을 예치해 나스닥 100 지수의 가격 변동에 대응할 수 있으며, 상승과 하락 방향 모두에 포지션을 설정할 수 있는 나스닥 선물 거래에 관심을 갖는 투자자가 많습니다.</p>\n    <p style=\"margin-bottom: 18px;\">하지만 선물 거래는 높은 레버리지와 변동성을 내포하고 있어, 계좌를 개설하고 주문을 넣는 제도적 규칙들을 정확히 숙지하지 않은 채 접근하면 순식간에 자본의 손실을 입을 수 있는 위험이 도사리고 있습니다. 입문 단계에서 반드시 이해해야 하는 나스닥 선물의 제도적 투자방법과 리스크 관리 원리를 인과관계 중심의 구조로 차분하게 설명해 드리겠습니다. 😊</p>\n\n    \n    <div style=\"background-color: #f8fafc; border: 1px solid #e2e8f0; border-radius: 8px; padding: 20px; margin: 25px 0;\">\n        <h3 style=\"font-size: 17px; color: #1e3a8a; margin: 0 0 12px 0; font-weight: bold;\">목차</h3>\n        <ul style=\"list-style-type: none; padding-left: 0; margin: 0;\">\n            <li style=\"margin-bottom: 8px;\"><a href=\"#section1\" style=\"color: #1a73e8; text-decoration: none; font-weight: bold;\">1. 투자 첫걸음: 해외선물 계좌 개설 및 제도적 자격 요건 📌</a></li>\n            <li style=\"margin-bottom: 8px;\"><a href=\"#section2\" style=\"color: #1a73e8; text-decoration: none; font-weight: bold;\">2. 거래 규격의 이해: E-mini(NQ)와 Micro E-mini(MNQ)의 구조 📊</a></li>\n            <li style=\"margin-bottom: 8px;\"><a href=\"#section3\" style=\"color: #1a73e8; text-decoration: none; font-weight: bold;\">3. 자본 통제의 기준: 개시증거금과 유지증거금의 시스템 ⚙️</a></li>\n            <li style=\"margin-bottom: 8px;\"><a href=\"#section4\" style=\"color: #1a73e8; text-decoration: none; font-weight: bold;\">4. 실전 매매 기술: 주문 방식의 세분화와 양방향 포지션 💡</a></li>\n            <li style=\"margin-bottom: 0;\"><a href=\"#section5\" style=\"color: #1a73e8; text-decoration: none; font-weight: bold;\">5. 파생상품의 만기 구조: 현금결제와 롤오버(Rollover) ⚠️</a></li>\n        </ul>\n    </div>\n\n    <p data-ke-size=\"size16\">&nbsp;</p>\n\n    \n    <h2 id=\"section1\" style=\"font-size: 22px; color: #1e3a8a; margin: 35px 0 15px; padding-bottom: 10px; border-bottom: 2px solid #e2e8f0; font-weight: bold;\">1. 투자 첫걸음: 해외선물 계좌 개설 및 제도적 자격 요건 📌</h2>\n    <p style=\"margin-bottom: 18px;\">개인 투자자가 미국 시카고상업거래소(CME)에 상장된 나스닥 선물을 매매하기 위해서는 파생상품 거래를 대행해 주는 <span style=\"background-color: #fffde7; padding: 2px 4px; border-radius: 3px;\">선물중개회사(FCM)</span>나 국내 증권사를 통해 해외선물 전용 계좌를 개설해야 합니다.</p>\n    <p style=\"margin-bottom: 18px;\">선물 거래는 위험성을 동반하기 때문에 국가의 규제 체계와 중개회사 정책에 따라 위험 고지 확인, 교육 이수, 모의거래, 최소 예탁금 등의 요건이 적용될 수 있습니다. 비대면 혹은 대면으로 계좌를 개설하는 과정에서 파생상품의 특성과 손실 가능성을 안내하는 구조화된 투자 위험성 가이드를 명확히 숙지하는 것이 필수적입니다.</p>\n\n    <p data-ke-size=\"size16\">&nbsp;</p>\n\n    \n    <h2 id=\"section2\" style=\"font-size: 22px; color: #1e3a8a; margin: 35px 0 15px; padding-bottom: 10px; border-bottom: 2px solid #e2e8f0; font-weight: bold;\">2. 거래 규격의 이해: E-mini(NQ)와 Micro E-mini(MNQ)의 구조 📊</h2>\n    <p style=\"margin-bottom: 18px;\">계좌 준비를 마쳤다면 내가 거래할 상품의 명세와 계약 단위를 온전히 이해해야 합니다. CME 거래소에 상장된 나스닥 지수 선물은 자본 규모에 맞춰 대응할 수 있도록 두 가지 대표 계약으로 세분화되어 유통됩니다. 표준 규격인 <strong>E-mini 나스닥 100(NQ)</strong>과 소액 투자용으로 축소 설계된 <strong>Micro E-mini 나스닥 100(MNQ)</strong>이 그 주인공입니다.</p>\n\n    <table style=\"width: 100%; border-collapse: collapse; margin: 20px 0; font-size: 15px; border: 1px solid #cbd5e1;\">\n        <thead>\n            <tr style=\"background-color: #f1f5f9; border-bottom: 2px solid #cbd5e1;\">\n                <th style=\"padding: 12px; text-align: left; font-weight: bold; color: #1e293b; border: 1px solid #cbd5e1; width: 25%;\">명세 항목</th>\n                <th style=\"padding: 12px; text-align: left; font-weight: bold; color: #1e293b; border: 1px solid #cbd5e1; width: 38%;\">E-mini 나스닥 100 (NQ)</th>\n                <th style=\"padding: 12px; text-align: left; font-weight: bold; color: #1e293b; border: 1px solid #cbd5e1; width: 37%;\">Micro E-mini 나스닥 100 (MNQ)</th>\n            </tr>\n        </thead>\n        <tbody>\n            <tr>\n                <td style=\"padding: 12px; font-weight: bold; color: #0f172a; border: 1px solid #cbd5e1;\">계약 승수</td>\n                <td style=\"padding: 12px; border: 1px solid #cbd5e1; color: #334155;\">지수 1포인트당 <strong>$20</strong></td>\n                <td style=\"padding: 12px; border: 1px solid #cbd5e1; color: #334155;\">지수 1포인트당 <strong>$2</strong> (NQ의 1/10 크기)</td>\n            </tr>\n            <tr style=\"background-color: #f8fafc;\">\n                <td style=\"padding: 12px; font-weight: bold; color: #0f172a; border: 1px solid #cbd5e1;\">최소 변동 폭 (Tick)</td>\n                <td style=\"padding: 12px; border: 1px solid #cbd5e1; color: #334155;\">0.25 포인트</td>\n                <td style=\"padding: 12px; border: 1px solid #cbd5e1; color: #334155;\">0.25 포인트</td>\n            </tr>\n            <tr>\n                <td style=\"padding: 12px; font-weight: bold; color: #0f172a; border: 1px solid #cbd5e1;\">1틱당 가치 (Tick Value)</td>\n                <td style=\"padding: 12px; border: 1px solid #cbd5e1; color: #1a73e8; font-weight: bold;\">$5.00</td>\n                <td style=\"padding: 12px; border: 1px solid #cbd5e1; color: #1a73e8; font-weight: bold;\">$0.50</td>\n            </tr>\n            <tr style=\"background-color: #f8fafc;\">\n                <td style=\"padding: 12px; font-weight: bold; color: #0f172a; border: 1px solid #cbd5e1;\">계약 규모의 특징</td>\n                <td style=\"padding: 12px; border: 1px solid #cbd5e1; color: #334155;\">큰 단위의 나스닥 100 익스포저 관리</td>\n                <td style=\"padding: 12px; border: 1px solid #cbd5e1; color: #334155;\">NQ보다 세분화된 단위의 익스포저 및 위험 관리</td>\n            </tr>\n        </tbody>\n    </table>\n\n    <p style=\"margin-bottom: 18px;\">MNQ는 NQ의 10분의 1 계약승수를 적용하므로, 동일한 지수 변동에서 발생하는 포인트당 손익 규모도 NQ의 10분의 1입니다. 결과적으로 투자자는 더 작은 단위로 포지션 규모를 조절할 수 있습니다.</p>\n\n    <p data-ke-size=\"size16\">&nbsp;</p>\n\n    \n    <h2 id=\"section3\" style=\"font-size: 22px; color: #1e3a8a; margin: 35px 0 15px; padding-bottom: 10px; border-bottom: 2px solid #e2e8f0; font-weight: bold;\">3. 자본 통제의 기준: 개시증거금과 유지증거금의 시스템 ⚙️</h2>\n    <p style=\"margin-bottom: 18px;\">선물 거래는 계약 명목가치 전액을 지급하는 대신, 계약 이행을 보증하기 위한 <strong>증거금(Margin)</strong>을 예치하는 구조로 운영됩니다. 이 증거금 체계는 포지션의 진입과 유지를 가르는 두 가지 기준선으로 구분됩니다.</p>\n\n    <ul style=\"margin: 0 0 15px 20px; padding: 0;\">\n        <li style=\"margin-bottom: 8px;\"><strong>개시증거금 (Initial Margin):</strong> 새로운 선물 포지션을 최초로 개설하기 위해 계좌에 보유하고 있어야 하는 포지션 개설을 위해 요구되는 최초 이행보증금 요건입니다.</li>\n        <li style=\"margin-bottom: 8px;\"><strong>유지증거금 (Maintenance Margin):</strong> 포지션을 잡은 이후 시장의 변동성에 노출되는 동안 계좌 내에 항상 남아 있어야 하는 최소 마지노선 기준 금액입니다. 유지증거금 수준은 거래소와 브로커의 정책, 시장 변동성 등에 따라 달라질 수 있습니다.</li>\n    </ul>\n\n    <p style=\"margin-bottom: 18px;\">계좌의 증거금 여력이 유지증거금 기준 아래로 내려가면 추가 증거금 납입 요구가 발생할 수 있습니다. 또한 브로커의 위험관리 정책에 따라 별도의 통지 없이 일부 또는 전부의 포지션이 청산될 수도 있으므로 상시 실시간 계좌 관리가 요구됩니다.</p>\n\n    <p data-ke-size=\"size16\">&nbsp;</p>\n\n    \n    <h2 id=\"section4\" style=\"font-size: 22px; color: #1e3a8a; margin: 35px 0 15px; padding-bottom: 10px; border-bottom: 2px solid #e2e8f0; font-weight: bold;\">4. 실전 매매 기술: 주문 방식의 세분화와 양방향 포지션 💡</h2>\n    <p style=\"margin-bottom: 18px;\">실제 MTS/HTS 프로그램의 주문창에 진입하면 시장 상황에 맞춰 매매를 체결시킬 다양한 주문 방식과 조우하게 됩니다. 대표적인 주문 메커니즘을 명확히 분리해 인지해야 합니다.</p>\n\n    <div style=\"background-color: #f8fafc; border: 1px solid #e2e8f0; border-radius: 8px; padding: 20px; margin-bottom: 25px;\">\n        <h4 style=\"font-size: 16px; color: #0f172a; margin: 0 0 12px 0; font-weight: bold;\">① 시장가 주문 (Market Order) 및 지정가 주문 (Limit Order)</h4>\n        <p style=\"margin-bottom: 15px; font-size: 15px; color: #475569; line-height: 1.6;\"><strong>시장가 주문</strong>은 현재 이용 가능한 호가를 기준으로 신속한 체결을 우선하는 주문입니다. 시장 상황에 따라 예상 가격과 실제 체결 가격 사이에 차이가 발생할 수 있습니다. 반면 <strong>지정가 주문</strong>은 원하는 가격 또는 그보다 유리한 가격에서만 체결되도록 가격 조건을 설정하는 주문입니다. 다만 시장이 해당 가격에 도달하지 않으면 체결되지 않을 수 있습니다.</p>\n        \n        <h4 style=\"font-size: 16px; color: #0f172a; margin: 15px 0 12px 0; font-weight: bold;\">② 스탑 주문 (Stop Order)과 손실 제한(Stop Loss)의 활용</h4>\n        <p style=\"margin-bottom: 0; font-size: 15px; color: #475569; line-height: 1.6;\"><strong>스탑 주문</strong>은 시세가 특정 조건 가격선에 다다랐을 때 주문이 비로소 활성화되는 조건부 주문 체계입니다. 이를 실무에서 내 잔고를 보호하기 위해 진입 가격 반대편에 손실 한도를 묶어두는 목적으로 배치하는 활용 사례를 <strong>스탑 로스(Stop Loss, 손실 제한 주문)</strong>라고 부릅니다. 다만 스탑 주문은 발동 가격을 기준으로 주문이 활성화되는 구조이므로, 급격한 변동 구간에서는 실제 체결가격이 설정가격과 다를 수 있습니다.</p>\n    </div>\n\n    <p style=\"margin-bottom: 18px;\">선물 거래의 특징 중 하나는 양방향성입니다. 거시 지표 분석을 통해 기초 지수가 위로 상승할 것으로 기대한다면 매수 진입인 <strong>롱(Long) 포지션</strong>을 설정하고, 반대로 시장의 하락 조정을 예상한다면 매도 진입인 <strong>숏(Short) 포지션</strong>을 선제적으로 취해 하락장 속에서도 이익 기회를 도출할 수 있습니다. 포지션의 방향성을 판단하기 전에 오더북의 실시간 흐름을 온전히 해석하고 대조하는 기법이 필요하다면 <a href=\"[나스닥 선물 보는 법]\" style=\"color: #1a73e8; text-decoration: none; font-weight: bold; border-bottom: 1px dotted #1a73e8;\">나스닥 선물 보는 법</a> 분석 가이드를 함께 학습해 보시는 것을 추천합니다.</p>\n\n    <p data-ke-size=\"size16\">&nbsp;</p>\n\n    \n    <h2 id=\"section5\" style=\"font-size: 22px; color: #1e3a8a; margin: 35px 0 15px; padding-bottom: 10px; border-bottom: 2px solid #e2e8f0; font-weight: bold;\">5. 파생상품의 만기 구조: 현금결제와 롤오버(Rollover) ⚠️</h2>\n    <p style=\"margin-bottom: 18px;\">일반 주식은 기업이 상장 폐지되지 않는 한 계속 보유할 수 있지만, 선물 계약은 태생적으로 생명 주기가 정해진 만기가 존재합니다. 나스닥 선물은 분기월인 <strong>3월, 6월, 9월, 12월의 세 번째 금요일</strong>에 만기일이 도래하도록 표준화되어 있습니다.</p>\n    <p style=\"margin-bottom: 18px;\">만기 전에 반대매매로 포지션을 종료하면 진입가격과 청산가격의 차이에 따른 손익이 계좌에 반영됩니다. 만기까지 보유한 계약은 CME가 정한 최종 정산가격을 기준으로 현금으로 최종 정산됩니다. 만기 이후에도 같은 방향의 선물 익스포저를 이어가려면, 통상 기존 근월물을 청산하고 다음 만기의 원월물에 새로 진입하는 <strong>롤오버(Rollover, 월물 교체)</strong>를 실시합니다. 롤오버 시점은 거래자가 선택할 수 있으며, 반드시 만기 주간에만 가능한 것은 아닙니다.</p>\n\n    <p style=\"margin-bottom: 18px;\">구체적인 야간 Globex 가동 주기나 세부 거래 스케줄 시간표는 <a href=\"[나스닥 선물 거래시간]\" style=\"color: #1a73e8; text-decoration: none; font-weight: bold; border-bottom: 1px dotted #1a73e8;\">나스닥 선물 거래시간</a> 가이드를 참고하시면 시간 관리에 도움이 됩니다.</p>\n\n    <p data-ke-size=\"size16\">&nbsp;</p>\n\n    \n    <div style=\"background-color: #f8fafc; padding: 25px; border-radius: 12px; margin: 25px 0; border: 1px solid #cbd5e1; box-shadow: 0 4px 6px -1px rgba(0,0,0,0.05);\">\n        <h3 style=\"font-size: 18px; color: #1e3a8a; margin: 0 0 20px 0; font-weight: bold; border-left: 4px solid #1a73e8; padding-left: 10px;\">나스닥 100 선물 실전 손익 체험 계산기 🧮</h3>\n        <p style=\"font-size: 15px; color: #475569; margin-bottom: 15px;\">진입 지수와 종료 지수, 포지션 방향에 따라 1계약의 총 규모와 내 잔고에 미치는 손익 가치가 어떻게 변동하는지 양방향으로 모의 연산해 볼 수 있는 체험 위젯입니다.</p>\n        \n        <div style=\"margin-bottom: 15px;\">\n            <label style=\"display: block; font-weight: bold; margin-bottom: 8px; color: #334155; font-size: 15px;\">① 선물 계약 등급 규격 선별</label>\n            <select id=\"multiplierSelect\" style=\"width: 100%; padding: 12px; border: 1px solid #cbd5e1; border-radius: 6px; font-size: 15px; background-color: #fff; color: #1e293b;\">\n                <option value=\"20\">E-mini 나스닥 100 (NQ - 승수 $20 / 틱당 $5.0)</option>\n                <option value=\"2\">Micro E-mini 나스닥 100 (MNQ - 승수 $2 / 틱당 $0.5)</option>\n            </select>\n        </div>\n\n        <div style=\"margin-bottom: 15px;\">\n            <label style=\"display: block; font-weight: bold; margin-bottom: 8px; color: #334155; font-size: 15px;\">② 진입 포지션 방향</label>\n            <select id=\"directionSelect\" style=\"width: 100%; padding: 12px; border: 1px solid #cbd5e1; border-radius: 6px; font-size: 15px; background-color: #fff; color: #1e293b;\">\n                <option value=\"long\">롱 (Long - 상승 예측)</option>\n                <option value=\"short\">숏 (Short - 하락 예측)</option>\n            </select>\n        </div>\n\n        <div style=\"margin-bottom: 15px;\">\n            <label style=\"display: block; font-weight: bold; margin-bottom: 8px; color: #334155; font-size: 15px;\">③ 포지션 진입 지수 (포인트)</label>\n            <input type=\"number\" id=\"entryIndex\" value=\"20000\" placeholder=\"예: 20000\" style=\"width: 100%; padding: 12px; border: 1px solid #cbd5e1; border-radius: 6px; font-size: 15px; color: #1e293b;\">\n        </div>\n\n        <div style=\"margin-bottom: 20px;\">\n            <label style=\"display: block; font-weight: bold; margin-bottom: 8px; color: #334155; font-size: 15px;\">④ 포지션 청산/종료 지수 (포인트)</label>\n            <input type=\"number\" id=\"exitIndex\" value=\"20100\" placeholder=\"예: 20100\" style=\"width: 100%; padding: 12px; border: 1px solid #cbd5e1; border-radius: 6px; font-size: 15px; color: #1e293b;\">\n        </div>\n\n        <button style=\"background-color: #1a73e8; color: white; border: none; padding: 14px 20px; border-radius: 6px; cursor: pointer; font-weight: bold; font-size: 16px; width: 100%; transition: background-color 0.2s;\">명목 가치 및 실전 손익 산출</button>\n\n        <div id=\"calcResultBox\" style=\"margin-top: 25px; padding: 20px; border: 1px solid #cbd5e1; border-radius: 8px; display: none; background-color: #ffffff;\">\n            <p style=\"margin: 0 0 10px 0; font-size: 15px; color: #475569;\">\n                진입 기준 1계약 총 명목 자산 규모 (USD): <br>\n                <span id=\"nominalValueResult\" style=\"color: #1e3a8a; font-weight: bold; font-size: 24px; line-height: 1.4;\"></span>\n            </p>\n            <p style=\"margin: 0 0 10px 0; font-size: 15px; color: #475569;\">\n                지수 변동 완료 시 발생할 가상 모의 손익 (USD): <br>\n                <span id=\"profitResult\" style=\"font-weight: bold; font-size: 20px; line-height: 1.4;\"></span>\n            </p>\n            <div style=\"border-top: 1px solid #f1f5f9; padding-top: 12px; font-size: 13px; color: #64748b;\">\n                ※ 위 결과는 입력값을 근간으로 도출된 단순 자산 환산 공식입니다. 반대 방향으로 같은 폭만큼 움직이면 동일한 규모의 손실이 발생합니다. 환율 변동과 수수료는 계측에서 제외되어 있으므로 투자 판단용 참고자료로만 활용해 주십시오.\n            </div>\n        </div>\n    </div>\n\n    \n\n    <p data-ke-size=\"size16\">&nbsp;</p>\n\n    \n    \n\n    \n    <div class=\"single-summary-card-container\">\n        <div class=\"single-summary-card\">\n            <div class=\"card-header\">\n                <span class=\"card-header-icon\">📑</span>\n                <h3>나스닥 선물 투자방법 절차 요약</h3>\n            </div>\n            <div class=\"card-content\">\n                <div class=\"section\"><strong>🎯 인프라 구축:</strong> 국내외 증권사 혹은 FCM을 통해 파생상품 전용 계좌를 확보하고 <span class=\"highlight\">위험 고지 동의 및 요건</span>을 완료합니다.</div>\n                <div class=\"section\"><strong>💎 대안의 선정:</strong> 자금 운용 스케줄에 맞춰 대형 표준형 NQ 계약 혹은 상대적으로 리스크 중량이 낮은 <span class=\"highlight\">마이크로 MNQ 계약</span>을 선별해 매매합니다.</div>\n                <div class=\"section\"><strong>🧮 리스크 차단 구조:</strong>\n                    <div class=\"formula\">유지증거금 기준 하회 ➡️ 추가 증거금 요구 또는 포지션 축소·청산 가능</div>\n                </div>\n                <div class=\"section\"><strong>⚡ 만기 리스크 제어:</strong> 매 3, 6, 9, 12월의 세 번째 금요일 최종 청산 충격을 방어하기 위해, 익스포저를 이어가려면 다음 월물로 <span class=\"highlight\">롤오버(Rollover)할 수 있습니다</span>.</div>\n            </div>\n            <div class=\"card-footer\">본 지침은 파생상품 메커니즘을 설명하는 금융 교육용 문서로 특정 거래 행위를 종용하거나 수익률을 보장하지 않습니다.</div>\n        </div>\n    </div>\n\n    <p data-ke-size=\"size16\">&nbsp;</p>\n\n    \n    <h2 style=\"font-size: 22px; color: #1e3a8a; margin: 35px 0 15px; padding-bottom: 10px; border-bottom: 2px solid #e2e8f0; font-weight: bold;\">자주 묻는 질문 ❓</h2>\n    <div style=\"margin: 25px 0; font-size: 15px; line-height: 1.6;\">\n        <div style=\"margin-bottom: 22px;\">\n            <div style=\"font-weight: bold; color: #0f172a; margin-bottom: 6px;\">Q: 계좌만 개설하고 예수금만 채워 넣으면 안정적인 수익 달성이 보장되나요?</div>\n            <div style=\"padding-left: 15px; color: #334155; border-left: 3px solid #cbd5e1;\">A: 아닙니다. 요건을 갖추면 시장 참여가 가능하지만, 선물 특유의 레버리지와 변동성으로 인해 제도적 참여 절차를 이행했다는 사실이 원금 보장이나 자본 수익을 확약하는 것은 아닙니다.</div>\n        </div>\n        <div style=\"margin-bottom: 22px;\">\n            <div style=\"font-weight: bold; color: #0f172a; margin-bottom: 6px;\">Q: 스탑 주문을 설정하면 지정한 가격에서 반드시 체결되나요?</div>\n            <div style=\"padding-left: 15px; color: #334155; border-left: 3px solid #cbd5e1;\">A: 아닙니다. 스탑 가격은 주문이 활성화되는 기준일 뿐입니다. 급격한 가격 변동이나 호가 공백이 발생하면 실제 체결가격은 설정한 스탑 가격과 달라질 수 있습니다.</div>\n        </div>\n        <div style=\"margin-bottom: 22px;\">\n            <div style=\"font-weight: bold; color: #0f172a; margin-bottom: 6px;\">Q: 롤오버(월물 교체)를 진행할 때 어떤 비용 변수가 작용하나요?</div>\n            <div style=\"padding-left: 15px; color: #334155; border-left: 3px solid #cbd5e1;\">A: 기존 계약 청산과 새 계약 진입 과정에서 거래 수수료와 매수·매도 호가 차이가 발생할 수 있습니다. 또한 근월물과 원월물의 가격이 다르기 때문에, 롤오버 전후의 계약가격도 같지 않을 수 있습니다.</div>\n        </div>\n    </div>\n\n    \n    \n\n    \n    <p style=\"margin-bottom: 18px;\">나스닥 선물 투자방법의 본질은 무조건적인 시세 예측에 있는 것이 아니라, 정형화된 계약 명세를 기반으로 내 자본금 규모에 맞는 증거금 한계선을 철저히 방어하는 통제 기술에 있습니다. 위험을 제어하기 위해 시스템적 규칙을 올바르게 응용하는 것이 거래 성패의 열쇠가 됩니다.</p>\n    <p style=\"margin-bottom: 18px;\">다음 가이드에서는 나스닥 선물 보는 법을 통해 현물지수, 선물가격, 베이시스를 실제 화면에서 어떻게 구분해 확인하는지 원리적 관점에서 상세히 다루어 보겠습니다. 계약 구조와 위험을 이해하는 것이 올바른 거래 판단의 출발점입니다. 더 궁금한 점이 있으시다면 언제든 편하게 아래 댓글로 의견 남겨주세요! 😊</p>\n\n    <div style=\"border-top: 1px dashed #cbd5e1; margin: 35px 0;\"></div>\n</div>",
  "description": "나스닥 지수 선물 거래에 입문하는 초보 트레이더를 위한 실무 지침서입니다. NQ/MNQ 명목 계약 가치 계산기부터 생존을 위한 스탑로스 설정법까지 한눈에 확인해 보세요.",
  "title": "나스닥 선물 투자방법: 계좌 개설부터 증거금 관리까지 완벽 가이드",
  "googleIndexStatus": "requested",
  "impressions": 0,
  "naverRequestedAt": "2026-07-18T02:58:46.996Z",
  "customCss": ".single-summary-card-container {\n            font-family: 'Noto Sans KR', sans-serif;\n            display: flex;\n            justify-content: center;\n            align-items: center;\n            padding: 20px 10px;\n            background-color: #f8fafc;\n            margin: 30px 0;\n            border-radius: 12px;\n            border: 1px solid #cbd5e1;\n        }\n        .single-summary-card {\n            width: 100%;\n            max-width: 700px;\n            background-color: #ffffff;\n            border-radius: 12px;\n            padding: 25px;\n            display: flex;\n            flex-direction: column;\n            box-sizing: border-box;\n            height: auto;\n        }\n        .single-summary-card .card-header {\n            display: flex;\n            align-items: center;\n            border-bottom: 2px solid #1e3a8a;\n            padding-bottom: 12px;\n            margin-bottom: 15px;\n        }\n        .single-summary-card .card-header-icon {\n            font-size: 30px;\n            color: #1e3a8a;\n            margin-right: 12px;\n        }\n        .single-summary-card .card-header h3 {\n            font-size: 22px;\n            color: #1e3a8a;\n            margin: 0;\n            line-height: 1.3;\n            font-weight: 700;\n        }\n        .single-summary-card .card-content {\n            font-size: 15px;\n            line-height: 1.6;\n            color: #334155;\n        }\n        .single-summary-card .card-content .section {\n            margin-bottom: 12px;\n        }\n        .single-summary-card .card-content strong {\n            color: #1e3a8a;\n            font-weight: 600;\n        }\n        .single-summary-card .card-content .highlight {\n            background-color: #f1f5f9;\n            padding: 2px 6px;\n            border-radius: 4px;\n            font-weight: bold;\n            color: #0f172a;\n        }\n        .single-summary-card .card-content .formula {\n            background-color: #f1f5f9;\n            padding: 8px 12px;\n            border-radius: 4px;\n            font-size: 0.95em;\n            text-align: center;\n            margin-top: 5px;\n            color: #1e293b;\n            font-weight: bold;\n            border: 1px solid #cbd5e1;\n        }\n        .single-summary-card .card-footer {\n            font-size: 13px;\n            color: #64748b;\n            text-align: center;\n            padding-top: 15px;\n            border-top: 1px dashed #cbd5e1;\n            margin-top: 15px;\n        }\n\n        @media (max-width: 768px) {\n            .single-summary-card {\n                padding: 18px;\n            }\n            .single-summary-card .card-header-icon {\n                font-size: 26px;\n            }\n            .single-summary-card .card-header h3 {\n                font-size: 18px;\n            }\n            .single-summary-card .card-content {\n                font-size: 14px;\n            }\n            .single-summary-card .card-footer {\n                font-size: 12px;\n            }\n        }",
  "mainKeyword": "나스닥 선물 투자방법",
  "publishHour": 8,
  "titleHistory": [],
  "googleRequestedAt": "2026-07-18T02:58:42.740Z",
  "thumbnail": "https://robo-advisor.kr/thumbnails/nasdaq-futures-investing.webp"
}